<?xml version="1.0" encoding="utf-8"?>
<modification>
  <name>  OptimBlog - Seo Url</name>
  <code>optimblog-seo</code>
  <version>3.0.0.0</version>
  <author>Dmitriy Khokhlov | optimlab.com</author>
  <link>http://optimlab.com</link>
  
  <file path="catalog/controller/startup/seo_url.php">
      <operation error="skip">
        <search><![CDATA[
				} elseif (isset($this->request->get['path'])) {
        ]]></search>
        <add position="replace"><![CDATA[
				} elseif (isset($this->request->get['path']) && !isset($this->request->get['information_id'])) {
        ]]></add>
      </operation>
  </file>
</modification>